PdmContext/ContextClustering.py
PdmContext/ContextGeneration.py
PdmContext/LightContextGeneration.py
PdmContext/Pipelines.py
PdmContext/__init__.py
PdmContext/utils/MovingPC.py
PdmContext/utils/__init__.py
PdmContext/utils/causal_discovery_functions.py
PdmContext/utils/dbconnector.py
PdmContext/utils/distances.py
PdmContext/utils/mapping_functions.py
PdmContext/utils/showcontext.py
PdmContext/utils/simulate_stream.py
PdmContext/utils/structure.py
pdmcontext-0.2.1.dist-info/METADATA
pdmcontext-0.2.1.dist-info/WHEEL
pdmcontext-0.2.1.dist-info/RECORD
