Metadata-Version: 2.4
Name: PdmContext
Version: 0.2.1
Summary: Contextualized Anomaly Detection
Project-URL: Homepage, https://github.com/agiannoul/PdMContext
Project-URL: Issues, https://github.com/agiannoul/PdMContext/issues
Project-URL: documentation, https://pd-m-context.vercel.app/
Author-email: Apostolos Giannoulidis <agiannous@csd.auth.gr>
Classifier: License :: OSI Approved :: MIT License
Classifier: Operating System :: OS Independent
Classifier: Programming Language :: Python :: 3
Requires-Python: >=3.8
Requires-Dist: matplotlib>=3.8
Requires-Dist: networkx>=3.0
Requires-Dist: numpy>=1.24
Requires-Dist: pandas>=2.0
